{
  "symbol": "ADA/USDT",
  "timeframe": "1h",
  "target_col": "target_1h",
  "train_bars": 1500,
  "test_bars": 250,
  "step_bars": 250,
  "min_confidence": 0.15,
  "fee_pct": 0.00075,
  "total_samples": 37070,
  "windows": 142,
  "traded_samples": 25811,
  "traded_coverage": 0.7271,
  "avg_direction_accuracy": 0.5241,
  "avg_traded_direction_accuracy": 0.5312,
  "avg_confidence": 0.3167,
  "total_gross_return_pct": 519.008,
  "total_net_return_pct": -3352.642,
  "avg_window_net_return_pct": -23.6102,
  "avg_mae": 0.006343,
  "window_results": [
    {
      "window_index": 1,
      "train_start": "2022-01-09T03:00:00",
      "train_end": "2022-03-12T14:00:00",
      "test_start": "2022-03-12T15:00:00",
      "test_end": "2022-03-23T00:00:00",
      "train_samples": 1500,
      "test_samples": 250,
      "coverage": 0.74,
      "traded_samples": 185,
      "direction_accuracy": 0.536,
      "traded_direction_accuracy": 0.5405,
      "gross_return_pct": 1.3311,
      "net_return_pct": -26.4189,
      "avg_confidence": 0.3182,
      "mae": 0.005146
    },
    {
      "window_index": 2,
      "train_start": "2022-01-19T13:00:00",
      "train_end": "2022-03-23T00:00:00",
      "test_start": "2022-03-23T01:00:00",
      "test_end": "2022-04-02T10:00:00",
      "train_samples": 1500,
      "test_samples": 250,
      "coverage": 0.716,
      "traded_samples": 179,
      "direction_accuracy": 0.584,
      "traded_direction_accuracy": 0.6034,
      "gross_return_pct": 17.7198,
      "net_return_pct": -9.1302,
      "avg_confidence": 0.286,
      "mae": 0.00712
    },
    {
      "window_index": 3,
      "train_start": "2022-01-29T23:00:00",
      "train_end": "2022-04-02T10:00:00",
      "test_start": "2022-04-02T11:00:00",
      "test_end": "2022-04-12T20:00:00",
      "train_samples": 1500,
      "test_samples": 250,
      "coverage": 0.752,
      "traded_samples": 188,
      "direction_accuracy": 0.524,
      "traded_direction_accuracy": 0.5479,
      "gross_return_pct": 11.5671,
      "net_return_pct": -16.6329,
      "avg_confidence": 0.3456,
      "mae": 0.006492
    },
    {
      "window_index": 4,
      "train_start": "2022-02-09T09:00:00",
      "train_end": "2022-04-12T20:00:00",
      "test_start": "2022-04-12T21:00:00",
      "test_end": "2022-04-23T06:00:00",
      "train_samples": 1500,
      "test_samples": 250,
      "coverage": 0.72,
      "traded_samples": 180,
      "direction_accuracy": 0.596,
      "traded_direction_accuracy": 0.6056,
      "gross_return_pct": 13.7606,
      "net_return_pct": -13.2394,
      "avg_confidence": 0.2896,
      "mae": 0.00454
    },
    {
      "window_index": 5,
      "train_start": "2022-02-19T19:00:00",
      "train_end": "2022-04-23T06:00:00",
      "test_start": "2022-04-23T07:00:00",
      "test_end": "2022-05-03T16:00:00",
      "train_samples": 1500,
      "test_samples": 250,
      "coverage": 0.644,
      "traded_samples": 161,
      "direction_accuracy": 0.564,
      "traded_direction_accuracy": 0.5466,
      "gross_return_pct": 10.586,
      "net_return_pct": -13.564,
      "avg_confidence": 0.2607,
      "mae": 0.005714
    },
    {
      "window_index": 6,
      "train_start": "2022-03-02T05:00:00",
      "train_end": "2022-05-03T16:00:00",
      "test_start": "2022-05-03T17:00:00",
      "test_end": "2022-05-14T02:00:00",
      "train_samples": 1500,
      "test_samples": 250,
      "coverage": 0.792,
      "traded_samples": 198,
      "direction_accuracy": 0.504,
      "traded_direction_accuracy": 0.4899,
      "gross_return_pct": -42.2902,
      "net_return_pct": -71.9902,
      "avg_confidence": 0.3919,
      "mae": 0.016491
    },
    {
      "window_index": 7,
      "train_start": "2022-03-12T15:00:00",
      "train_end": "2022-05-14T02:00:00",
      "test_start": "2022-05-14T03:00:00",
      "test_end": "2022-05-24T12:00:00",
      "train_samples": 1500,
      "test_samples": 250,
      "coverage": 0.672,
      "traded_samples": 168,
      "direction_accuracy": 0.492,
      "traded_direction_accuracy": 0.5298,
      "gross_return_pct": 29.0238,
      "net_return_pct": 3.8238,
      "avg_confidence": 0.2804,
      "mae": 0.010093
    },
    {
      "window_index": 8,
      "train_start": "2022-03-23T01:00:00",
      "train_end": "2022-05-24T12:00:00",
      "test_start": "2022-05-24T13:00:00",
      "test_end": "2022-06-03T22:00:00",
      "train_samples": 1500,
      "test_samples": 250,
      "coverage": 0.724,
      "traded_samples": 181,
      "direction_accuracy": 0.524,
      "traded_direction_accuracy": 0.547,
      "gross_return_pct": -4.0486,
      "net_return_pct": -31.1986,
      "avg_confidence": 0.3115,
      "mae": 0.009518
    },
    {
      "window_index": 9,
      "train_start": "2022-04-02T11:00:00",
      "train_end": "2022-06-03T22:00:00",
      "test_start": "2022-06-03T23:00:00",
      "test_end": "2022-06-14T08:00:00",
      "train_samples": 1500,
      "test_samples": 250,
      "coverage": 0.728,
      "traded_samples": 182,
      "direction_accuracy": 0.496,
      "traded_direction_accuracy": 0.522,
      "gross_return_pct": 5.1102,
      "net_return_pct": -22.1898,
      "avg_confidence": 0.3137,
      "mae": 0.011852
    },
    {
      "window_index": 10,
      "train_start": "2022-04-12T21:00:00",
      "train_end": "2022-06-14T08:00:00",
      "test_start": "2022-06-14T09:00:00",
      "test_end": "2022-06-24T18:00:00",
      "train_samples": 1500,
      "test_samples": 250,
      "coverage": 0.704,
      "traded_samples": 176,
      "direction_accuracy": 0.5,
      "traded_direction_accuracy": 0.5341,
      "gross_return_pct": -4.0003,
      "net_return_pct": -30.4003,
      "avg_confidence": 0.3127,
      "mae": 0.010354
    },
    {
      "window_index": 11,
      "train_start": "2022-04-23T07:00:00",
      "train_end": "2022-06-24T18:00:00",
      "test_start": "2022-06-24T19:00:00",
      "test_end": "2022-07-05T04:00:00",
      "train_samples": 1500,
      "test_samples": 250,
      "coverage": 0.68,
      "traded_samples": 170,
      "direction_accuracy": 0.52,
      "traded_direction_accuracy": 0.5412,
      "gross_return_pct": 2.6655,
      "net_return_pct": -22.8345,
      "avg_confidence": 0.28,
      "mae": 0.006303
    },
    {
      "window_index": 12,
      "train_start": "2022-05-03T17:00:00",
      "train_end": "2022-07-05T04:00:00",
      "test_start": "2022-07-05T05:00:00",
      "test_end": "2022-07-15T14:00:00",
      "train_samples": 1500,
      "test_samples": 250,
      "coverage": 0.712,
      "traded_samples": 178,
      "direction_accuracy": 0.52,
      "traded_direction_accuracy": 0.5112,
      "gross_return_pct": -0.1501,
      "net_return_pct": -26.8501,
      "avg_confidence": 0.2942,
      "mae": 0.005694
    },
    {
      "window_index": 13,
      "train_start": "2022-05-14T03:00:00",
      "train_end": "2022-07-15T14:00:00",
      "test_start": "2022-07-15T15:00:00",
      "test_end": "2022-07-26T00:00:00",
      "train_samples": 1500,
      "test_samples": 250,
      "coverage": 0.772,
      "traded_samples": 193,
      "direction_accuracy": 0.572,
      "traded_direction_accuracy": 0.5596,
      "gross_return_pct": 5.2468,
      "net_return_pct": -23.7032,
      "avg_confidence": 0.3663,
      "mae": 0.007574
    },
    {
      "window_index": 14,
      "train_start": "2022-05-24T13:00:00",
      "train_end": "2022-07-26T00:00:00",
      "test_start": "2022-07-26T01:00:00",
      "test_end": "2022-08-05T10:00:00",
      "train_samples": 1500,
      "test_samples": 250,
      "coverage": 0.72,
      "traded_samples": 180,
      "direction_accuracy": 0.548,
      "traded_direction_accuracy": 0.5889,
      "gross_return_pct": 20.3582,
      "net_return_pct": -6.6418,
      "avg_confidence": 0.323,
      "mae": 0.006824
    },
    {
      "window_index": 15,
      "train_start": "2022-06-03T23:00:00",
      "train_end": "2022-08-05T10:00:00",
      "test_start": "2022-08-05T11:00:00",
      "test_end": "2022-08-15T20:00:00",
      "train_samples": 1500,
      "test_samples": 250,
      "coverage": 0.752,
      "traded_samples": 188,
      "direction_accuracy": 0.596,
      "traded_direction_accuracy": 0.6011,
      "gross_return_pct": 14.0742,
      "net_return_pct": -14.1258,
      "avg_confidence": 0.2949,
      "mae": 0.005053
    },
    {
      "window_index": 16,
      "train_start": "2022-06-14T09:00:00",
      "train_end": "2022-08-15T20:00:00",
      "test_start": "2022-08-15T21:00:00",
      "test_end": "2022-08-26T06:00:00",
      "train_samples": 1500,
      "test_samples": 250,
      "coverage": 0.704,
      "traded_samples": 176,
      "direction_accuracy": 0.496,
      "traded_direction_accuracy": 0.5341,
      "gross_return_pct": 8.5311,
      "net_return_pct": -17.8689,
      "avg_confidence": 0.2834,
      "mae": 0.006663
    },
    {
      "window_index": 17,
      "train_start": "2022-06-24T19:00:00",
      "train_end": "2022-08-26T06:00:00",
      "test_start": "2022-08-26T07:00:00",
      "test_end": "2022-09-05T16:00:00",
      "train_samples": 1500,
      "test_samples": 250,
      "coverage": 0.688,
      "traded_samples": 172,
      "direction_accuracy": 0.604,
      "traded_direction_accuracy": 0.5698,
      "gross_return_pct": 19.6797,
      "net_return_pct": -6.1203,
      "avg_confidence": 0.2898,
      "mae": 0.005645
    },
    {
      "window_index": 18,
      "train_start": "2022-07-05T05:00:00",
      "train_end": "2022-09-05T16:00:00",
      "test_start": "2022-09-05T17:00:00",
      "test_end": "2022-09-16T02:00:00",
      "train_samples": 1500,
      "test_samples": 250,
      "coverage": 0.704,
      "traded_samples": 176,
      "direction_accuracy": 0.508,
      "traded_direction_accuracy": 0.5227,
      "gross_return_pct": 5.6115,
      "net_return_pct": -20.7885,
      "avg_confidence": 0.2941,
      "mae": 0.005847
    },
    {
      "window_index": 19,
      "train_start": "2022-07-15T15:00:00",
      "train_end": "2022-09-16T02:00:00",
      "test_start": "2022-09-16T03:00:00",
      "test_end": "2022-09-26T12:00:00",
      "train_samples": 1500,
      "test_samples": 250,
      "coverage": 0.724,
      "traded_samples": 181,
      "direction_accuracy": 0.5,
      "traded_direction_accuracy": 0.5083,
      "gross_return_pct": -1.0196,
      "net_return_pct": -28.1696,
      "avg_confidence": 0.3017,
      "mae": 0.006288
    },
    {
      "window_index": 20,
      "train_start": "2022-07-26T01:00:00",
      "train_end": "2022-09-26T12:00:00",
      "test_start": "2022-09-26T13:00:00",
      "test_end": "2022-10-06T22:00:00",
      "train_samples": 1500,
      "test_samples": 250,
      "coverage": 0.884,
      "traded_samples": 221,
      "direction_accuracy": 0.516,
      "traded_direction_accuracy": 0.5204,
      "gross_return_pct": 5.3289,
      "net_return_pct": -27.8211,
      "avg_confidence": 0.466,
      "mae": 0.003483
    },
    {
      "window_index": 21,
      "train_start": "2022-08-05T11:00:00",
      "train_end": "2022-10-06T22:00:00",
      "test_start": "2022-10-06T23:00:00",
      "test_end": "2022-10-17T08:00:00",
      "train_samples": 1500,
      "test_samples": 250,
      "coverage": 0.708,
      "traded_samples": 177,
      "direction_accuracy": 0.48,
      "traded_direction_accuracy": 0.4689,
      "gross_return_pct": -15.8828,
      "net_return_pct": -42.4328,
      "avg_confidence": 0.313,
      "mae": 0.003962
    },
    {
      "window_index": 22,
      "train_start": "2022-08-15T21:00:00",
      "train_end": "2022-10-17T08:00:00",
      "test_start": "2022-10-17T09:00:00",
      "test_end": "2022-10-27T18:00:00",
      "train_samples": 1500,
      "test_samples": 250,
      "coverage": 0.716,
      "traded_samples": 179,
      "direction_accuracy": 0.516,
      "traded_direction_accuracy": 0.5196,
      "gross_return_pct": -6.2797,
      "net_return_pct": -33.1297,
      "avg_confidence": 0.3265,
      "mae": 0.005156
    },
    {
      "window_index": 23,
      "train_start": "2022-08-26T07:00:00",
      "train_end": "2022-10-27T18:00:00",
      "test_start": "2022-10-27T19:00:00",
      "test_end": "2022-11-07T04:00:00",
      "train_samples": 1500,
      "test_samples": 250,
      "coverage": 0.736,
      "traded_samples": 184,
      "direction_accuracy": 0.568,
      "traded_direction_accuracy": 0.5707,
      "gross_return_pct": 3.2772,
      "net_return_pct": -24.3228,
      "avg_confidence": 0.311,
      "mae": 0.005924
    },
    {
      "window_index": 24,
      "train_start": "2022-09-05T17:00:00",
      "train_end": "2022-11-07T04:00:00",
      "test_start": "2022-11-07T05:00:00",
      "test_end": "2022-11-17T14:00:00",
      "train_samples": 1500,
      "test_samples": 250,
      "coverage": 0.78,
      "traded_samples": 195,
      "direction_accuracy": 0.564,
      "traded_direction_accuracy": 0.5846,
      "gross_return_pct": 10.7995,
      "net_return_pct": -18.4505,
      "avg_confidence": 0.3841,
      "mae": 0.008337
    },
    {
      "window_index": 25,
      "train_start": "2022-09-16T03:00:00",
      "train_end": "2022-11-17T14:00:00",
      "test_start": "2022-11-17T15:00:00",
      "test_end": "2022-11-28T00:00:00",
      "train_samples": 1500,
      "test_samples": 250,
      "coverage": 0.74,
      "traded_samples": 185,
      "direction_accuracy": 0.496,
      "traded_direction_accuracy": 0.4973,
      "gross_return_pct": -1.987,
      "net_return_pct": -29.737,
      "avg_confidence": 0.292,
      "mae": 0.004612
    },
    {
      "window_index": 26,
      "train_start": "2022-09-26T13:00:00",
      "train_end": "2022-11-28T00:00:00",
      "test_start": "2022-11-28T01:00:00",
      "test_end": "2022-12-08T10:00:00",
      "train_samples": 1500,
      "test_samples": 250,
      "coverage": 0.728,
      "traded_samples": 182,
      "direction_accuracy": 0.532,
      "traded_direction_accuracy": 0.5549,
      "gross_return_pct": 5.4976,
      "net_return_pct": -21.8024,
      "avg_confidence": 0.2878,
      "mae": 0.003205
    },
    {
      "window_index": 27,
      "train_start": "2022-10-06T23:00:00",
      "train_end": "2022-12-08T10:00:00",
      "test_start": "2022-12-08T11:00:00",
      "test_end": "2022-12-18T20:00:00",
      "train_samples": 1500,
      "test_samples": 250,
      "coverage": 0.756,
      "traded_samples": 189,
      "direction_accuracy": 0.572,
      "traded_direction_accuracy": 0.5714,
      "gross_return_pct": 10.2124,
      "net_return_pct": -18.1376,
      "avg_confidence": 0.335,
      "mae": 0.003556
    },
    {
      "window_index": 28,
      "train_start": "2022-10-17T09:00:00",
      "train_end": "2022-12-18T20:00:00",
      "test_start": "2022-12-18T21:00:00",
      "test_end": "2022-12-29T06:00:00",
      "train_samples": 1500,
      "test_samples": 250,
      "coverage": 0.684,
      "traded_samples": 171,
      "direction_accuracy": 0.548,
      "traded_direction_accuracy": 0.5848,
      "gross_return_pct": 7.9697,
      "net_return_pct": -17.6803,
      "avg_confidence": 0.3154,
      "mae": 0.00332
    },
    {
      "window_index": 29,
      "train_start": "2022-10-27T19:00:00",
      "train_end": "2022-12-29T06:00:00",
      "test_start": "2022-12-29T07:00:00",
      "test_end": "2023-01-08T16:00:00",
      "train_samples": 1500,
      "test_samples": 250,
      "coverage": 0.8,
      "traded_samples": 200,
      "direction_accuracy": 0.524,
      "traded_direction_accuracy": 0.54,
      "gross_return_pct": 2.9953,
      "net_return_pct": -27.0047,
      "avg_confidence": 0.3852,
      "mae": 0.003905
    },
    {
      "window_index": 30,
      "train_start": "2022-11-07T05:00:00",
      "train_end": "2023-01-08T16:00:00",
      "test_start": "2023-01-08T17:00:00",
      "test_end": "2023-01-19T02:00:00",
      "train_samples": 1500,
      "test_samples": 250,
      "coverage": 0.752,
      "traded_samples": 188,
      "direction_accuracy": 0.532,
      "traded_direction_accuracy": 0.5532,
      "gross_return_pct": -9.2055,
      "net_return_pct": -37.4055,
      "avg_confidence": 0.3263,
      "mae": 0.007232
    },
    {
      "window_index": 31,
      "train_start": "2022-11-17T15:00:00",
      "train_end": "2023-01-19T02:00:00",
      "test_start": "2023-01-19T03:00:00",
      "test_end": "2023-01-29T12:00:00",
      "train_samples": 1500,
      "test_samples": 250,
      "coverage": 0.732,
      "traded_samples": 183,
      "direction_accuracy": 0.564,
      "traded_direction_accuracy": 0.5738,
      "gross_return_pct": 9.6751,
      "net_return_pct": -17.7749,
      "avg_confidence": 0.3654,
      "mae": 0.006156
    },
    {
      "window_index": 32,
      "train_start": "2022-11-28T01:00:00",
      "train_end": "2023-01-29T12:00:00",
      "test_start": "2023-01-29T13:00:00",
      "test_end": "2023-02-08T22:00:00",
      "train_samples": 1500,
      "test_samples": 250,
      "coverage": 0.776,
      "traded_samples": 194,
      "direction_accuracy": 0.52,
      "traded_direction_accuracy": 0.5619,
      "gross_return_pct": 8.2272,
      "net_return_pct": -20.8728,
      "avg_confidence": 0.3466,
      "mae": 0.005055
    },
    {
      "window_index": 33,
      "train_start": "2022-12-08T11:00:00",
      "train_end": "2023-02-08T22:00:00",
      "test_start": "2023-02-08T23:00:00",
      "test_end": "2023-02-19T08:00:00",
      "train_samples": 1500,
      "test_samples": 250,
      "coverage": 0.684,
      "traded_samples": 171,
      "direction_accuracy": 0.532,
      "traded_direction_accuracy": 0.5263,
      "gross_return_pct": -1.9817,
      "net_return_pct": -27.6317,
      "avg_confidence": 0.2926,
      "mae": 0.005175
    },
    {
      "window_index": 34,
      "train_start": "2022-12-18T21:00:00",
      "train_end": "2023-02-19T08:00:00",
      "test_start": "2023-02-19T09:00:00",
      "test_end": "2023-03-01T18:00:00",
      "train_samples": 1500,
      "test_samples": 250,
      "coverage": 0.684,
      "traded_samples": 171,
      "direction_accuracy": 0.512,
      "traded_direction_accuracy": 0.4971,
      "gross_return_pct": 0.4621,
      "net_return_pct": -25.1879,
      "avg_confidence": 0.2804,
      "mae": 0.004434
    },
    {
      "window_index": 35,
      "train_start": "2022-12-29T07:00:00",
      "train_end": "2023-03-01T18:00:00",
      "test_start": "2023-03-01T19:00:00",
      "test_end": "2023-03-12T04:00:00",
      "train_samples": 1500,
      "test_samples": 250,
      "coverage": 0.668,
      "traded_samples": 167,
      "direction_accuracy": 0.52,
      "traded_direction_accuracy": 0.5509,
      "gross_return_pct": 19.1193,
      "net_return_pct": -5.9307,
      "avg_confidence": 0.2659,
      "mae": 0.004977
    },
    {
      "window_index": 36,
      "train_start": "2023-01-08T17:00:00",
      "train_end": "2023-03-12T04:00:00",
      "test_start": "2023-03-12T05:00:00",
      "test_end": "2023-03-22T14:00:00",
      "train_samples": 1500,
      "test_samples": 250,
      "coverage": 0.72,
      "traded_samples": 180,
      "direction_accuracy": 0.556,
      "traded_direction_accuracy": 0.5944,
      "gross_return_pct": 18.5325,
      "net_return_pct": -8.4675,
      "avg_confidence": 0.3265,
      "mae": 0.007401
    },
    {
      "window_index": 37,
      "train_start": "2023-01-19T03:00:00",
      "train_end": "2023-03-22T14:00:00",
      "test_start": "2023-03-22T15:00:00",
      "test_end": "2023-04-02T01:00:00",
      "train_samples": 1500,
      "test_samples": 250,
      "coverage": 0.756,
      "traded_samples": 189,
      "direction_accuracy": 0.548,
      "traded_direction_accuracy": 0.5556,
      "gross_return_pct": 4.6887,
      "net_return_pct": -23.6613,
      "avg_confidence": 0.3379,
      "mae": 0.005929
    },
    {
      "window_index": 38,
      "train_start": "2023-01-29T13:00:00",
      "train_end": "2023-04-02T01:00:00",
      "test_start": "2023-04-02T02:00:00",
      "test_end": "2023-04-12T11:00:00",
      "train_samples": 1500,
      "test_samples": 250,
      "coverage": 0.732,
      "traded_samples": 183,
      "direction_accuracy": 0.52,
      "traded_direction_accuracy": 0.5628,
      "gross_return_pct": -3.3014,
      "net_return_pct": -30.7514,
      "avg_confidence": 0.3484,
      "mae": 0.004471
    },
    {
      "window_index": 39,
      "train_start": "2023-02-08T23:00:00",
      "train_end": "2023-04-12T11:00:00",
      "test_start": "2023-04-12T12:00:00",
      "test_end": "2023-04-22T21:00:00",
      "train_samples": 1500,
      "test_samples": 250,
      "coverage": 0.776,
      "traded_samples": 194,
      "direction_accuracy": 0.56,
      "traded_direction_accuracy": 0.5309,
      "gross_return_pct": 2.2212,
      "net_return_pct": -26.8788,
      "avg_confidence": 0.3653,
      "mae": 0.005474
    },
    {
      "window_index": 40,
      "train_start": "2023-02-19T09:00:00",
      "train_end": "2023-04-22T21:00:00",
      "test_start": "2023-04-22T22:00:00",
      "test_end": "2023-05-03T07:00:00",
      "train_samples": 1500,
      "test_samples": 250,
      "coverage": 0.772,
      "traded_samples": 193,
      "direction_accuracy": 0.532,
      "traded_direction_accuracy": 0.5648,
      "gross_return_pct": -0.3663,
      "net_return_pct": -29.3163,
      "avg_confidence": 0.3346,
      "mae": 0.00428
    },
    {
      "window_index": 41,
      "train_start": "2023-03-01T19:00:00",
      "train_end": "2023-05-03T07:00:00",
      "test_start": "2023-05-03T08:00:00",
      "test_end": "2023-05-13T17:00:00",
      "train_samples": 1500,
      "test_samples": 250,
      "coverage": 0.744,
      "traded_samples": 186,
      "direction_accuracy": 0.536,
      "traded_direction_accuracy": 0.5376,
      "gross_return_pct": 5.3178,
      "net_return_pct": -22.5822,
      "avg_confidence": 0.3189,
      "mae": 0.004268
    },
    {
      "window_index": 42,
      "train_start": "2023-03-12T05:00:00",
      "train_end": "2023-05-13T17:00:00",
      "test_start": "2023-05-13T18:00:00",
      "test_end": "2023-05-24T03:00:00",
      "train_samples": 1500,
      "test_samples": 250,
      "coverage": 0.804,
      "traded_samples": 201,
      "direction_accuracy": 0.548,
      "traded_direction_accuracy": 0.5473,
      "gross_return_pct": 7.5626,
      "net_return_pct": -22.5874,
      "avg_confidence": 0.3817,
      "mae": 0.003232
    },
    {
      "window_index": 43,
      "train_start": "2023-03-22T15:00:00",
      "train_end": "2023-05-24T03:00:00",
      "test_start": "2023-05-24T04:00:00",
      "test_end": "2023-06-03T13:00:00",
      "train_samples": 1500,
      "test_samples": 250,
      "coverage": 0.756,
      "traded_samples": 189,
      "direction_accuracy": 0.524,
      "traded_direction_accuracy": 0.5397,
      "gross_return_pct": 1.956,
      "net_return_pct": -26.394,
      "avg_confidence": 0.3434,
      "mae": 0.002817
    },
    {
      "window_index": 44,
      "train_start": "2023-04-02T02:00:00",
      "train_end": "2023-06-03T13:00:00",
      "test_start": "2023-06-03T14:00:00",
      "test_end": "2023-06-13T23:00:00",
      "train_samples": 1500,
      "test_samples": 250,
      "coverage": 0.844,
      "traded_samples": 211,
      "direction_accuracy": 0.516,
      "traded_direction_accuracy": 0.5261,
      "gross_return_pct": -0.8974,
      "net_return_pct": -32.5474,
      "avg_confidence": 0.4473,
      "mae": 0.007301
    },
    {
      "window_index": 45,
      "train_start": "2023-04-12T12:00:00",
      "train_end": "2023-06-13T23:00:00",
      "test_start": "2023-06-14T00:00:00",
      "test_end": "2023-06-24T09:00:00",
      "train_samples": 1500,
      "test_samples": 250,
      "coverage": 0.768,
      "traded_samples": 192,
      "direction_accuracy": 0.576,
      "traded_direction_accuracy": 0.5677,
      "gross_return_pct": 6.4814,
      "net_return_pct": -22.3186,
      "avg_confidence": 0.3243,
      "mae": 0.005571
    },
    {
      "window_index": 46,
      "train_start": "2023-04-22T22:00:00",
      "train_end": "2023-06-24T09:00:00",
      "test_start": "2023-06-24T10:00:00",
      "test_end": "2023-07-04T19:00:00",
      "train_samples": 1500,
      "test_samples": 250,
      "coverage": 0.732,
      "traded_samples": 183,
      "direction_accuracy": 0.564,
      "traded_direction_accuracy": 0.5519,
      "gross_return_pct": 15.4872,
      "net_return_pct": -11.9628,
      "avg_confidence": 0.3165,
      "mae": 0.005123
    },
    {
      "window_index": 47,
      "train_start": "2023-05-03T08:00:00",
      "train_end": "2023-07-04T19:00:00",
      "test_start": "2023-07-04T20:00:00",
      "test_end": "2023-07-15T05:00:00",
      "train_samples": 1500,
      "test_samples": 250,
      "coverage": 0.72,
      "traded_samples": 180,
      "direction_accuracy": 0.504,
      "traded_direction_accuracy": 0.5333,
      "gross_return_pct": -25.5996,
      "net_return_pct": -52.5996,
      "avg_confidence": 0.2938,
      "mae": 0.005724
    },
    {
      "window_index": 48,
      "train_start": "2023-05-13T18:00:00",
      "train_end": "2023-07-15T05:00:00",
      "test_start": "2023-07-15T06:00:00",
      "test_end": "2023-07-25T15:00:00",
      "train_samples": 1500,
      "test_samples": 250,
      "coverage": 0.72,
      "traded_samples": 180,
      "direction_accuracy": 0.52,
      "traded_direction_accuracy": 0.5333,
      "gross_return_pct": 7.5358,
      "net_return_pct": -19.4642,
      "avg_confidence": 0.3041,
      "mae": 0.004772
    },
    {
      "window_index": 49,
      "train_start": "2023-05-24T04:00:00",
      "train_end": "2023-07-25T15:00:00",
      "test_start": "2023-07-25T16:00:00",
      "test_end": "2023-08-05T01:00:00",
      "train_samples": 1500,
      "test_samples": 250,
      "coverage": 0.7,
      "traded_samples": 175,
      "direction_accuracy": 0.532,
      "traded_direction_accuracy": 0.5429,
      "gross_return_pct": 9.12,
      "net_return_pct": -17.13,
      "avg_confidence": 0.2955,
      "mae": 0.003061
    },
    {
      "window_index": 50,
      "train_start": "2023-06-03T14:00:00",
      "train_end": "2023-08-05T01:00:00",
      "test_start": "2023-08-05T02:00:00",
      "test_end": "2023-08-15T11:00:00",
      "train_samples": 1500,
      "test_samples": 250,
      "coverage": 0.752,
      "traded_samples": 188,
      "direction_accuracy": 0.54,
      "traded_direction_accuracy": 0.5585,
      "gross_return_pct": 5.954,
      "net_return_pct": -22.246,
      "avg_confidence": 0.3186,
      "mae": 0.00259
    },
    {
      "window_index": 51,
      "train_start": "2023-06-14T00:00:00",
      "train_end": "2023-08-15T11:00:00",
      "test_start": "2023-08-15T12:00:00",
      "test_end": "2023-08-25T21:00:00",
      "train_samples": 1500,
      "test_samples": 250,
      "coverage": 0.744,
      "traded_samples": 186,
      "direction_accuracy": 0.532,
      "traded_direction_accuracy": 0.5376,
      "gross_return_pct": 4.9711,
      "net_return_pct": -22.9289,
      "avg_confidence": 0.3175,
      "mae": 0.004651
    },
    {
      "window_index": 52,
      "train_start": "2023-06-24T10:00:00",
      "train_end": "2023-08-25T21:00:00",
      "test_start": "2023-08-25T22:00:00",
      "test_end": "2023-09-05T07:00:00",
      "train_samples": 1500,
      "test_samples": 250,
      "coverage": 0.7,
      "traded_samples": 175,
      "direction_accuracy": 0.564,
      "traded_direction_accuracy": 0.5829,
      "gross_return_pct": 7.1082,
      "net_return_pct": -19.1418,
      "avg_confidence": 0.288,
      "mae": 0.003173
    },
    {
      "window_index": 53,
      "train_start": "2023-07-04T20:00:00",
      "train_end": "2023-09-05T07:00:00",
      "test_start": "2023-09-05T08:00:00",
      "test_end": "2023-09-15T17:00:00",
      "train_samples": 1500,
      "test_samples": 250,
      "coverage": 0.756,
      "traded_samples": 189,
      "direction_accuracy": 0.552,
      "traded_direction_accuracy": 0.5503,
      "gross_return_pct": 9.3026,
      "net_return_pct": -19.0474,
      "avg_confidence": 0.3385,
      "mae": 0.003004
    },
    {
      "window_index": 54,
      "train_start": "2023-07-15T06:00:00",
      "train_end": "2023-09-15T17:00:00",
      "test_start": "2023-09-15T18:00:00",
      "test_end": "2023-09-26T03:00:00",
      "train_samples": 1500,
      "test_samples": 250,
      "coverage": 0.764,
      "traded_samples": 191,
      "direction_accuracy": 0.512,
      "traded_direction_accuracy": 0.5288,
      "gross_return_pct": 2.9647,
      "net_return_pct": -25.6853,
      "avg_confidence": 0.3461,
      "mae": 0.002746
    },
    {
      "window_index": 55,
      "train_start": "2023-07-25T16:00:00",
      "train_end": "2023-09-26T03:00:00",
      "test_start": "2023-09-26T04:00:00",
      "test_end": "2023-10-06T13:00:00",
      "train_samples": 1500,
      "test_samples": 250,
      "coverage": 0.784,
      "traded_samples": 196,
      "direction_accuracy": 0.524,
      "traded_direction_accuracy": 0.5153,
      "gross_return_pct": -3.8416,
      "net_return_pct": -33.2416,
      "avg_confidence": 0.3839,
      "mae": 0.003911
    },
    {
      "window_index": 56,
      "train_start": "2023-08-05T02:00:00",
      "train_end": "2023-10-06T13:00:00",
      "test_start": "2023-10-06T14:00:00",
      "test_end": "2023-10-16T23:00:00",
      "train_samples": 1500,
      "test_samples": 250,
      "coverage": 0.76,
      "traded_samples": 190,
      "direction_accuracy": 0.556,
      "traded_direction_accuracy": 0.5526,
      "gross_return_pct": 4.291,
      "net_return_pct": -24.209,
      "avg_confidence": 0.3282,
      "mae": 0.002496
    },
    {
      "window_index": 57,
      "train_start": "2023-08-15T12:00:00",
      "train_end": "2023-10-16T23:00:00",
      "test_start": "2023-10-17T00:00:00",
      "test_end": "2023-10-27T09:00:00",
      "train_samples": 1500,
      "test_samples": 250,
      "coverage": 0.716,
      "traded_samples": 179,
      "direction_accuracy": 0.488,
      "traded_direction_accuracy": 0.5028,
      "gross_return_pct": -8.0582,
      "net_return_pct": -34.9082,
      "avg_confidence": 0.3514,
      "mae": 0.005279
    },
    {
      "window_index": 58,
      "train_start": "2023-08-25T22:00:00",
      "train_end": "2023-10-27T09:00:00",
      "test_start": "2023-10-27T10:00:00",
      "test_end": "2023-11-06T19:00:00",
      "train_samples": 1500,
      "test_samples": 250,
      "coverage": 0.728,
      "traded_samples": 182,
      "direction_accuracy": 0.512,
      "traded_direction_accuracy": 0.511,
      "gross_return_pct": -12.2434,
      "net_return_pct": -39.5434,
      "avg_confidence": 0.3458,
      "mae": 0.005958
    },
    {
      "window_index": 59,
      "train_start": "2023-09-05T08:00:00",
      "train_end": "2023-11-06T19:00:00",
      "test_start": "2023-11-06T20:00:00",
      "test_end": "2023-11-17T05:00:00",
      "train_samples": 1500,
      "test_samples": 250,
      "coverage": 0.7,
      "traded_samples": 175,
      "direction_accuracy": 0.54,
      "traded_direction_accuracy": 0.5314,
      "gross_return_pct": -2.5128,
      "net_return_pct": -28.7628,
      "avg_confidence": 0.3227,
      "mae": 0.007488
    },
    {
      "window_index": 60,
      "train_start": "2023-09-15T18:00:00",
      "train_end": "2023-11-17T05:00:00",
      "test_start": "2023-11-17T06:00:00",
      "test_end": "2023-11-27T15:00:00",
      "train_samples": 1500,
      "test_samples": 250,
      "coverage": 0.732,
      "traded_samples": 183,
      "direction_accuracy": 0.54,
      "traded_direction_accuracy": 0.5301,
      "gross_return_pct": 8.6054,
      "net_return_pct": -18.8446,
      "avg_confidence": 0.2952,
      "mae": 0.005594
    },
    {
      "window_index": 61,
      "train_start": "2023-09-26T04:00:00",
      "train_end": "2023-11-27T15:00:00",
      "test_start": "2023-11-27T16:00:00",
      "test_end": "2023-12-08T01:00:00",
      "train_samples": 1500,
      "test_samples": 250,
      "coverage": 0.72,
      "traded_samples": 180,
      "direction_accuracy": 0.532,
      "traded_direction_accuracy": 0.5278,
      "gross_return_pct": -4.7289,
      "net_return_pct": -31.7289,
      "avg_confidence": 0.3003,
      "mae": 0.005209
    },
    {
      "window_index": 62,
      "train_start": "2023-10-06T14:00:00",
      "train_end": "2023-12-08T01:00:00",
      "test_start": "2023-12-08T02:00:00",
      "test_end": "2023-12-18T11:00:00",
      "train_samples": 1500,
      "test_samples": 250,
      "coverage": 0.824,
      "traded_samples": 206,
      "direction_accuracy": 0.504,
      "traded_direction_accuracy": 0.5,
      "gross_return_pct": -9.3665,
      "net_return_pct": -40.2665,
      "avg_confidence": 0.405,
      "mae": 0.011687
    },
    {
      "window_index": 63,
      "train_start": "2023-10-17T00:00:00",
      "train_end": "2023-12-18T11:00:00",
      "test_start": "2023-12-18T12:00:00",
      "test_end": "2023-12-28T21:00:00",
      "train_samples": 1500,
      "test_samples": 250,
      "coverage": 0.716,
      "traded_samples": 179,
      "direction_accuracy": 0.584,
      "traded_direction_accuracy": 0.5922,
      "gross_return_pct": 17.521,
      "net_return_pct": -9.329,
      "avg_confidence": 0.3234,
      "mae": 0.007387
    },
    {
      "window_index": 64,
      "train_start": "2023-10-27T10:00:00",
      "train_end": "2023-12-28T21:00:00",
      "test_start": "2023-12-28T22:00:00",
      "test_end": "2024-01-08T07:00:00",
      "train_samples": 1500,
      "test_samples": 250,
      "coverage": 0.796,
      "traded_samples": 199,
      "direction_accuracy": 0.504,
      "traded_direction_accuracy": 0.5025,
      "gross_return_pct": -13.9304,
      "net_return_pct": -43.7804,
      "avg_confidence": 0.3988,
      "mae": 0.006711
    },
    {
      "window_index": 65,
      "train_start": "2023-11-06T20:00:00",
      "train_end": "2024-01-08T07:00:00",
      "test_start": "2024-01-08T08:00:00",
      "test_end": "2024-01-18T17:00:00",
      "train_samples": 1500,
      "test_samples": 250,
      "coverage": 0.808,
      "traded_samples": 202,
      "direction_accuracy": 0.544,
      "traded_direction_accuracy": 0.5545,
      "gross_return_pct": 23.652,
      "net_return_pct": -6.648,
      "avg_confidence": 0.3387,
      "mae": 0.007218
    },
    {
      "window_index": 66,
      "train_start": "2023-11-17T06:00:00",
      "train_end": "2024-01-18T17:00:00",
      "test_start": "2024-01-18T18:00:00",
      "test_end": "2024-01-29T03:00:00",
      "train_samples": 1500,
      "test_samples": 250,
      "coverage": 0.648,
      "traded_samples": 162,
      "direction_accuracy": 0.488,
      "traded_direction_accuracy": 0.4815,
      "gross_return_pct": 1.3408,
      "net_return_pct": -22.9592,
      "avg_confidence": 0.2802,
      "mae": 0.005215
    },
    {
      "window_index": 67,
      "train_start": "2023-11-27T16:00:00",
      "train_end": "2024-01-29T03:00:00",
      "test_start": "2024-01-29T04:00:00",
      "test_end": "2024-02-08T13:00:00",
      "train_samples": 1500,
      "test_samples": 250,
      "coverage": 0.7,
      "traded_samples": 175,
      "direction_accuracy": 0.492,
      "traded_direction_accuracy": 0.4743,
      "gross_return_pct": 0.9998,
      "net_return_pct": -25.2502,
      "avg_confidence": 0.2965,
      "mae": 0.004996
    },
    {
      "window_index": 68,
      "train_start": "2023-12-08T02:00:00",
      "train_end": "2024-02-08T13:00:00",
      "test_start": "2024-02-08T14:00:00",
      "test_end": "2024-02-18T23:00:00",
      "train_samples": 1500,
      "test_samples": 250,
      "coverage": 0.676,
      "traded_samples": 169,
      "direction_accuracy": 0.468,
      "traded_direction_accuracy": 0.4734,
      "gross_return_pct": -7.2822,
      "net_return_pct": -32.6322,
      "avg_confidence": 0.2787,
      "mae": 0.00611
    },
    {
      "window_index": 69,
      "train_start": "2023-12-18T12:00:00",
      "train_end": "2024-02-18T23:00:00",
      "test_start": "2024-02-19T00:00:00",
      "test_end": "2024-02-29T09:00:00",
      "train_samples": 1500,
      "test_samples": 250,
      "coverage": 0.696,
      "traded_samples": 174,
      "direction_accuracy": 0.532,
      "traded_direction_accuracy": 0.5517,
      "gross_return_pct": 25.1537,
      "net_return_pct": -0.9463,
      "avg_confidence": 0.291,
      "mae": 0.00689
    },
    {
      "window_index": 70,
      "train_start": "2023-12-28T22:00:00",
      "train_end": "2024-02-29T09:00:00",
      "test_start": "2024-02-29T10:00:00",
      "test_end": "2024-03-10T19:00:00",
      "train_samples": 1500,
      "test_samples": 250,
      "coverage": 0.744,
      "traded_samples": 186,
      "direction_accuracy": 0.504,
      "traded_direction_accuracy": 0.5323,
      "gross_return_pct": 13.0064,
      "net_return_pct": -14.8936,
      "avg_confidence": 0.3323,
      "mae": 0.008896
    },
    {
      "window_index": 71,
      "train_start": "2024-01-08T08:00:00",
      "train_end": "2024-03-10T19:00:00",
      "test_start": "2024-03-10T20:00:00",
      "test_end": "2024-03-21T05:00:00",
      "train_samples": 1500,
      "test_samples": 250,
      "coverage": 0.812,
      "traded_samples": 203,
      "direction_accuracy": 0.568,
      "traded_direction_accuracy": 0.5862,
      "gross_return_pct": 23.7396,
      "net_return_pct": -6.7104,
      "avg_confidence": 0.3934,
      "mae": 0.010224
    },
    {
      "window_index": 72,
      "train_start": "2024-01-18T18:00:00",
      "train_end": "2024-03-21T05:00:00",
      "test_start": "2024-03-21T06:00:00",
      "test_end": "2024-03-31T15:00:00",
      "train_samples": 1500,
      "test_samples": 250,
      "coverage": 0.7,
      "traded_samples": 175,
      "direction_accuracy": 0.496,
      "traded_direction_accuracy": 0.5029,
      "gross_return_pct": -1.5674,
      "net_return_pct": -27.8174,
      "avg_confidence": 0.274,
      "mae": 0.00491
    },
    {
      "window_index": 73,
      "train_start": "2024-01-29T04:00:00",
      "train_end": "2024-03-31T15:00:00",
      "test_start": "2024-03-31T16:00:00",
      "test_end": "2024-04-11T01:00:00",
      "train_samples": 1500,
      "test_samples": 250,
      "coverage": 0.756,
      "traded_samples": 189,
      "direction_accuracy": 0.512,
      "traded_direction_accuracy": 0.5238,
      "gross_return_pct": -2.0976,
      "net_return_pct": -30.4476,
      "avg_confidence": 0.3247,
      "mae": 0.00512
    },
    {
      "window_index": 74,
      "train_start": "2024-02-08T14:00:00",
      "train_end": "2024-04-11T01:00:00",
      "test_start": "2024-04-11T02:00:00",
      "test_end": "2024-04-21T11:00:00",
      "train_samples": 1500,
      "test_samples": 250,
      "coverage": 0.72,
      "traded_samples": 180,
      "direction_accuracy": 0.544,
      "traded_direction_accuracy": 0.5444,
      "gross_return_pct": -4.9282,
      "net_return_pct": -31.9282,
      "avg_confidence": 0.3229,
      "mae": 0.010465
    },
    {
      "window_index": 75,
      "train_start": "2024-02-19T00:00:00",
      "train_end": "2024-04-21T11:00:00",
      "test_start": "2024-04-21T12:00:00",
      "test_end": "2024-05-01T21:00:00",
      "train_samples": 1500,
      "test_samples": 250,
      "coverage": 0.72,
      "traded_samples": 180,
      "direction_accuracy": 0.452,
      "traded_direction_accuracy": 0.4556,
      "gross_return_pct": -9.8179,
      "net_return_pct": -36.8179,
      "avg_confidence": 0.2949,
      "mae": 0.005916
    },
    {
      "window_index": 76,
      "train_start": "2024-02-29T10:00:00",
      "train_end": "2024-05-01T21:00:00",
      "test_start": "2024-05-01T22:00:00",
      "test_end": "2024-05-12T07:00:00",
      "train_samples": 1500,
      "test_samples": 250,
      "coverage": 0.744,
      "traded_samples": 186,
      "direction_accuracy": 0.512,
      "traded_direction_accuracy": 0.5054,
      "gross_return_pct": 3.7367,
      "net_return_pct": -24.1633,
      "avg_confidence": 0.3116,
      "mae": 0.004481
    },
    {
      "window_index": 77,
      "train_start": "2024-03-10T20:00:00",
      "train_end": "2024-05-12T07:00:00",
      "test_start": "2024-05-12T08:00:00",
      "test_end": "2024-05-22T17:00:00",
      "train_samples": 1500,
      "test_samples": 250,
      "coverage": 0.832,
      "traded_samples": 208,
      "direction_accuracy": 0.536,
      "traded_direction_accuracy": 0.5385,
      "gross_return_pct": 0.0631,
      "net_return_pct": -31.1369,
      "avg_confidence": 0.4162,
      "mae": 0.005128
    },
    {
      "window_index": 78,
      "train_start": "2024-03-21T06:00:00",
      "train_end": "2024-05-22T17:00:00",
      "test_start": "2024-05-22T18:00:00",
      "test_end": "2024-06-02T03:00:00",
      "train_samples": 1500,
      "test_samples": 250,
      "coverage": 0.76,
      "traded_samples": 190,
      "direction_accuracy": 0.528,
      "traded_direction_accuracy": 0.5368,
      "gross_return_pct": 5.9155,
      "net_return_pct": -22.5845,
      "avg_confidence": 0.2965,
      "mae": 0.003595
    },
    {
      "window_index": 79,
      "train_start": "2024-03-31T16:00:00",
      "train_end": "2024-06-02T03:00:00",
      "test_start": "2024-06-02T04:00:00",
      "test_end": "2024-06-12T13:00:00",
      "train_samples": 1500,
      "test_samples": 250,
      "coverage": 0.72,
      "traded_samples": 180,
      "direction_accuracy": 0.508,
      "traded_direction_accuracy": 0.4778,
      "gross_return_pct": -3.3533,
      "net_return_pct": -30.3533,
      "avg_confidence": 0.3078,
      "mae": 0.004211
    },
    {
      "window_index": 80,
      "train_start": "2024-04-11T02:00:00",
      "train_end": "2024-06-12T13:00:00",
      "test_start": "2024-06-12T14:00:00",
      "test_end": "2024-06-22T23:00:00",
      "train_samples": 1500,
      "test_samples": 250,
      "coverage": 0.724,
      "traded_samples": 181,
      "direction_accuracy": 0.56,
      "traded_direction_accuracy": 0.5856,
      "gross_return_pct": 8.148,
      "net_return_pct": -19.002,
      "avg_confidence": 0.302,
      "mae": 0.005143
    },
    {
      "window_index": 81,
      "train_start": "2024-04-21T12:00:00",
      "train_end": "2024-06-22T23:00:00",
      "test_start": "2024-06-23T00:00:00",
      "test_end": "2024-07-03T09:00:00",
      "train_samples": 1500,
      "test_samples": 250,
      "coverage": 0.728,
      "traded_samples": 182,
      "direction_accuracy": 0.516,
      "traded_direction_accuracy": 0.522,
      "gross_return_pct": 0.4323,
      "net_return_pct": -26.8677,
      "avg_confidence": 0.3071,
      "mae": 0.004592
    },
    {
      "window_index": 82,
      "train_start": "2024-05-01T22:00:00",
      "train_end": "2024-07-03T09:00:00",
      "test_start": "2024-07-03T10:00:00",
      "test_end": "2024-07-13T19:00:00",
      "train_samples": 1500,
      "test_samples": 250,
      "coverage": 0.768,
      "traded_samples": 192,
      "direction_accuracy": 0.52,
      "traded_direction_accuracy": 0.5156,
      "gross_return_pct": -6.6137,
      "net_return_pct": -35.4137,
      "avg_confidence": 0.3333,
      "mae": 0.007707
    },
    {
      "window_index": 83,
      "train_start": "2024-05-12T08:00:00",
      "train_end": "2024-07-13T19:00:00",
      "test_start": "2024-07-13T20:00:00",
      "test_end": "2024-07-24T05:00:00",
      "train_samples": 1500,
      "test_samples": 250,
      "coverage": 0.728,
      "traded_samples": 182,
      "direction_accuracy": 0.516,
      "traded_direction_accuracy": 0.5,
      "gross_return_pct": -6.7148,
      "net_return_pct": -34.0148,
      "avg_confidence": 0.3071,
      "mae": 0.005787
    },
    {
      "window_index": 84,
      "train_start": "2024-05-22T18:00:00",
      "train_end": "2024-07-24T05:00:00",
      "test_start": "2024-07-24T06:00:00",
      "test_end": "2024-08-03T15:00:00",
      "train_samples": 1500,
      "test_samples": 250,
      "coverage": 0.672,
      "traded_samples": 168,
      "direction_accuracy": 0.54,
      "traded_direction_accuracy": 0.5536,
      "gross_return_pct": -4.2763,
      "net_return_pct": -29.4763,
      "avg_confidence": 0.2618,
      "mae": 0.005319
    },
    {
      "window_index": 85,
      "train_start": "2024-06-02T04:00:00",
      "train_end": "2024-08-03T15:00:00",
      "test_start": "2024-08-03T16:00:00",
      "test_end": "2024-08-14T01:00:00",
      "train_samples": 1500,
      "test_samples": 250,
      "coverage": 0.78,
      "traded_samples": 195,
      "direction_accuracy": 0.476,
      "traded_direction_accuracy": 0.4872,
      "gross_return_pct": -17.5001,
      "net_return_pct": -46.7501,
      "avg_confidence": 0.3751,
      "mae": 0.007898
    },
    {
      "window_index": 86,
      "train_start": "2024-06-12T14:00:00",
      "train_end": "2024-08-14T01:00:00",
      "test_start": "2024-08-14T02:00:00",
      "test_end": "2024-08-24T11:00:00",
      "train_samples": 1500,
      "test_samples": 250,
      "coverage": 0.736,
      "traded_samples": 184,
      "direction_accuracy": 0.504,
      "traded_direction_accuracy": 0.4891,
      "gross_return_pct": 7.5971,
      "net_return_pct": -20.0029,
      "avg_confidence": 0.3156,
      "mae": 0.004958
    },
    {
      "window_index": 87,
      "train_start": "2024-06-23T00:00:00",
      "train_end": "2024-08-24T11:00:00",
      "test_start": "2024-08-24T12:00:00",
      "test_end": "2024-09-03T21:00:00",
      "train_samples": 1500,
      "test_samples": 250,
      "coverage": 0.684,
      "traded_samples": 171,
      "direction_accuracy": 0.528,
      "traded_direction_accuracy": 0.5146,
      "gross_return_pct": 3.5616,
      "net_return_pct": -22.0884,
      "avg_confidence": 0.2771,
      "mae": 0.005473
    },
    {
      "window_index": 88,
      "train_start": "2024-07-03T10:00:00",
      "train_end": "2024-09-03T21:00:00",
      "test_start": "2024-09-03T22:00:00",
      "test_end": "2024-09-14T07:00:00",
      "train_samples": 1500,
      "test_samples": 250,
      "coverage": 0.68,
      "traded_samples": 170,
      "direction_accuracy": 0.536,
      "traded_direction_accuracy": 0.5059,
      "gross_return_pct": -2.0925,
      "net_return_pct": -27.5925,
      "avg_confidence": 0.2925,
      "mae": 0.00527
    },
    {
      "window_index": 89,
      "train_start": "2024-07-13T20:00:00",
      "train_end": "2024-09-14T07:00:00",
      "test_start": "2024-09-14T08:00:00",
      "test_end": "2024-09-24T17:00:00",
      "train_samples": 1500,
      "test_samples": 250,
      "coverage": 0.796,
      "traded_samples": 199,
      "direction_accuracy": 0.496,
      "traded_direction_accuracy": 0.5025,
      "gross_return_pct": -5.5744,
      "net_return_pct": -35.4244,
      "avg_confidence": 0.3501,
      "mae": 0.004326
    },
    {
      "window_index": 90,
      "train_start": "2024-07-24T06:00:00",
      "train_end": "2024-09-24T17:00:00",
      "test_start": "2024-09-24T18:00:00",
      "test_end": "2024-10-05T03:00:00",
      "train_samples": 1500,
      "test_samples": 250,
      "coverage": 0.676,
      "traded_samples": 169,
      "direction_accuracy": 0.508,
      "traded_direction_accuracy": 0.5385,
      "gross_return_pct": 9.3494,
      "net_return_pct": -16.0006,
      "avg_confidence": 0.3201,
      "mae": 0.005702
    },
    {
      "window_index": 91,
      "train_start": "2024-08-03T16:00:00",
      "train_end": "2024-10-05T03:00:00",
      "test_start": "2024-10-05T04:00:00",
      "test_end": "2024-10-15T13:00:00",
      "train_samples": 1500,
      "test_samples": 250,
      "coverage": 0.652,
      "traded_samples": 163,
      "direction_accuracy": 0.532,
      "traded_direction_accuracy": 0.5399,
      "gross_return_pct": -1.1475,
      "net_return_pct": -25.5975,
      "avg_confidence": 0.2556,
      "mae": 0.004748
    },
    {
      "window_index": 92,
      "train_start": "2024-08-14T02:00:00",
      "train_end": "2024-10-15T13:00:00",
      "test_start": "2024-10-15T14:00:00",
      "test_end": "2024-10-25T23:00:00",
      "train_samples": 1500,
      "test_samples": 250,
      "coverage": 0.68,
      "traded_samples": 170,
      "direction_accuracy": 0.44,
      "traded_direction_accuracy": 0.4471,
      "gross_return_pct": -9.6135,
      "net_return_pct": -35.1135,
      "avg_confidence": 0.2789,
      "mae": 0.004913
    },
    {
      "window_index": 93,
      "train_start": "2024-08-24T12:00:00",
      "train_end": "2024-10-25T23:00:00",
      "test_start": "2024-10-26T00:00:00",
      "test_end": "2024-11-05T09:00:00",
      "train_samples": 1500,
      "test_samples": 250,
      "coverage": 0.716,
      "traded_samples": 179,
      "direction_accuracy": 0.504,
      "traded_direction_accuracy": 0.5084,
      "gross_return_pct": 8.1724,
      "net_return_pct": -18.6776,
      "avg_confidence": 0.285,
      "mae": 0.0048
    },
    {
      "window_index": 94,
      "train_start": "2024-09-03T22:00:00",
      "train_end": "2024-11-05T09:00:00",
      "test_start": "2024-11-05T10:00:00",
      "test_end": "2024-11-15T19:00:00",
      "train_samples": 1500,
      "test_samples": 250,
      "coverage": 0.76,
      "traded_samples": 190,
      "direction_accuracy": 0.488,
      "traded_direction_accuracy": 0.4947,
      "gross_return_pct": -5.6692,
      "net_return_pct": -34.1692,
      "avg_confidence": 0.3671,
      "mae": 0.012542
    },
    {
      "window_index": 95,
      "train_start": "2024-09-14T08:00:00",
      "train_end": "2024-11-15T19:00:00",
      "test_start": "2024-11-15T20:00:00",
      "test_end": "2024-11-26T05:00:00",
      "train_samples": 1500,
      "test_samples": 250,
      "coverage": 0.732,
      "traded_samples": 183,
      "direction_accuracy": 0.5,
      "traded_direction_accuracy": 0.5246,
      "gross_return_pct": -0.1468,
      "net_return_pct": -27.5968,
      "avg_confidence": 0.3051,
      "mae": 0.014876
    },
    {
      "window_index": 96,
      "train_start": "2024-09-24T18:00:00",
      "train_end": "2024-11-26T05:00:00",
      "test_start": "2024-11-26T06:00:00",
      "test_end": "2024-12-06T15:00:00",
      "train_samples": 1500,
      "test_samples": 250,
      "coverage": 0.732,
      "traded_samples": 183,
      "direction_accuracy": 0.592,
      "traded_direction_accuracy": 0.5902,
      "gross_return_pct": 57.5686,
      "net_return_pct": 30.1186,
      "avg_confidence": 0.3113,
      "mae": 0.011297
    },
    {
      "window_index": 97,
      "train_start": "2024-10-05T04:00:00",
      "train_end": "2024-12-06T15:00:00",
      "test_start": "2024-12-06T16:00:00",
      "test_end": "2024-12-17T01:00:00",
      "train_samples": 1500,
      "test_samples": 250,
      "coverage": 0.756,
      "traded_samples": 189,
      "direction_accuracy": 0.504,
      "traded_direction_accuracy": 0.4921,
      "gross_return_pct": 4.6294,
      "net_return_pct": -23.7206,
      "avg_confidence": 0.3377,
      "mae": 0.009927
    },
    {
      "window_index": 98,
      "train_start": "2024-10-15T14:00:00",
      "train_end": "2024-12-17T01:00:00",
      "test_start": "2024-12-17T02:00:00",
      "test_end": "2024-12-27T11:00:00",
      "train_samples": 1500,
      "test_samples": 250,
      "coverage": 0.792,
      "traded_samples": 198,
      "direction_accuracy": 0.5,
      "traded_direction_accuracy": 0.5152,
      "gross_return_pct": 14.2882,
      "net_return_pct": -15.4118,
      "avg_confidence": 0.4161,
      "mae": 0.010034
    },
    {
      "window_index": 99,
      "train_start": "2024-10-26T00:00:00",
      "train_end": "2024-12-27T11:00:00",
      "test_start": "2024-12-27T12:00:00",
      "test_end": "2025-01-06T21:00:00",
      "train_samples": 1500,
      "test_samples": 250,
      "coverage": 0.66,
      "traded_samples": 165,
      "direction_accuracy": 0.504,
      "traded_direction_accuracy": 0.5333,
      "gross_return_pct": 16.9324,
      "net_return_pct": -7.8176,
      "avg_confidence": 0.2495,
      "mae": 0.007018
    },
    {
      "window_index": 100,
      "train_start": "2024-11-05T10:00:00",
      "train_end": "2025-01-06T21:00:00",
      "test_start": "2025-01-06T22:00:00",
      "test_end": "2025-01-17T07:00:00",
      "train_samples": 1500,
      "test_samples": 250,
      "coverage": 0.712,
      "traded_samples": 178,
      "direction_accuracy": 0.464,
      "traded_direction_accuracy": 0.4607,
      "gross_return_pct": -15.0942,
      "net_return_pct": -41.7942,
      "avg_confidence": 0.3148,
      "mae": 0.010207
    },
    {
      "window_index": 101,
      "train_start": "2024-11-15T20:00:00",
      "train_end": "2025-01-17T07:00:00",
      "test_start": "2025-01-17T08:00:00",
      "test_end": "2025-01-27T17:00:00",
      "train_samples": 1500,
      "test_samples": 250,
      "coverage": 0.748,
      "traded_samples": 187,
      "direction_accuracy": 0.532,
      "traded_direction_accuracy": 0.5561,
      "gross_return_pct": 32.792,
      "net_return_pct": 4.742,
      "avg_confidence": 0.3244,
      "mae": 0.009243
    },
    {
      "window_index": 102,
      "train_start": "2024-11-26T06:00:00",
      "train_end": "2025-01-27T17:00:00",
      "test_start": "2025-01-27T18:00:00",
      "test_end": "2025-02-07T03:00:00",
      "train_samples": 1500,
      "test_samples": 250,
      "coverage": 0.712,
      "traded_samples": 178,
      "direction_accuracy": 0.468,
      "traded_direction_accuracy": 0.4663,
      "gross_return_pct": -1.6935,
      "net_return_pct": -28.3935,
      "avg_confidence": 0.3402,
      "mae": 0.011076
    },
    {
      "window_index": 103,
      "train_start": "2024-12-06T16:00:00",
      "train_end": "2025-02-07T03:00:00",
      "test_start": "2025-02-07T04:00:00",
      "test_end": "2025-02-17T13:00:00",
      "train_samples": 1500,
      "test_samples": 250,
      "coverage": 0.724,
      "traded_samples": 181,
      "direction_accuracy": 0.48,
      "traded_direction_accuracy": 0.4972,
      "gross_return_pct": -13.8335,
      "net_return_pct": -40.9835,
      "avg_confidence": 0.2926,
      "mae": 0.008337
    },
    {
      "window_index": 104,
      "train_start": "2024-12-17T02:00:00",
      "train_end": "2025-02-17T13:00:00",
      "test_start": "2025-02-17T14:00:00",
      "test_end": "2025-02-27T23:00:00",
      "train_samples": 1500,
      "test_samples": 250,
      "coverage": 0.68,
      "traded_samples": 170,
      "direction_accuracy": 0.444,
      "traded_direction_accuracy": 0.4529,
      "gross_return_pct": -12.6663,
      "net_return_pct": -38.1663,
      "avg_confidence": 0.2766,
      "mae": 0.008717
    },
    {
      "window_index": 105,
      "train_start": "2024-12-27T12:00:00",
      "train_end": "2025-02-27T23:00:00",
      "test_start": "2025-02-28T00:00:00",
      "test_end": "2025-03-10T09:00:00",
      "train_samples": 1500,
      "test_samples": 250,
      "coverage": 0.768,
      "traded_samples": 192,
      "direction_accuracy": 0.568,
      "traded_direction_accuracy": 0.5573,
      "gross_return_pct": 71.0927,
      "net_return_pct": 42.2927,
      "avg_confidence": 0.3355,
      "mae": 0.015685
    },
    {
      "window_index": 106,
      "train_start": "2025-01-06T22:00:00",
      "train_end": "2025-03-10T09:00:00",
      "test_start": "2025-03-10T10:00:00",
      "test_end": "2025-03-20T19:00:00",
      "train_samples": 1500,
      "test_samples": 250,
      "coverage": 0.652,
      "traded_samples": 163,
      "direction_accuracy": 0.548,
      "traded_direction_accuracy": 0.589,
      "gross_return_pct": 25.9691,
      "net_return_pct": 1.5191,
      "avg_confidence": 0.2558,
      "mae": 0.007719
    },
    {
      "window_index": 107,
      "train_start": "2025-01-17T08:00:00",
      "train_end": "2025-03-20T19:00:00",
      "test_start": "2025-03-20T20:00:00",
      "test_end": "2025-03-31T05:00:00",
      "train_samples": 1500,
      "test_samples": 250,
      "coverage": 0.784,
      "traded_samples": 196,
      "direction_accuracy": 0.516,
      "traded_direction_accuracy": 0.5357,
      "gross_return_pct": 8.3544,
      "net_return_pct": -21.0456,
      "avg_confidence": 0.349,
      "mae": 0.005864
    },
    {
      "window_index": 108,
      "train_start": "2025-01-27T18:00:00",
      "train_end": "2025-03-31T05:00:00",
      "test_start": "2025-03-31T06:00:00",
      "test_end": "2025-04-10T15:00:00",
      "train_samples": 1500,
      "test_samples": 250,
      "coverage": 0.676,
      "traded_samples": 169,
      "direction_accuracy": 0.548,
      "traded_direction_accuracy": 0.5325,
      "gross_return_pct": -6.2834,
      "net_return_pct": -31.6334,
      "avg_confidence": 0.2864,
      "mae": 0.009817
    },
    {
      "window_index": 109,
      "train_start": "2025-02-07T04:00:00",
      "train_end": "2025-04-10T15:00:00",
      "test_start": "2025-04-10T16:00:00",
      "test_end": "2025-04-21T01:00:00",
      "train_samples": 1500,
      "test_samples": 250,
      "coverage": 0.708,
      "traded_samples": 177,
      "direction_accuracy": 0.528,
      "traded_direction_accuracy": 0.5763,
      "gross_return_pct": 22.9879,
      "net_return_pct": -3.5621,
      "avg_confidence": 0.2885,
      "mae": 0.005433
    },
    {
      "window_index": 110,
      "train_start": "2025-02-17T14:00:00",
      "train_end": "2025-04-21T01:00:00",
      "test_start": "2025-04-21T02:00:00",
      "test_end": "2025-05-01T11:00:00",
      "train_samples": 1500,
      "test_samples": 250,
      "coverage": 0.712,
      "traded_samples": 178,
      "direction_accuracy": 0.524,
      "traded_direction_accuracy": 0.5056,
      "gross_return_pct": -4.5616,
      "net_return_pct": -31.2616,
      "avg_confidence": 0.3345,
      "mae": 0.006716
    },
    {
      "window_index": 111,
      "train_start": "2025-02-28T00:00:00",
      "train_end": "2025-05-01T11:00:00",
      "test_start": "2025-05-01T12:00:00",
      "test_end": "2025-05-11T21:00:00",
      "train_samples": 1500,
      "test_samples": 250,
      "coverage": 0.684,
      "traded_samples": 171,
      "direction_accuracy": 0.548,
      "traded_direction_accuracy": 0.5789,
      "gross_return_pct": 11.0147,
      "net_return_pct": -14.6353,
      "avg_confidence": 0.2905,
      "mae": 0.006922
    },
    {
      "window_index": 112,
      "train_start": "2025-03-10T10:00:00",
      "train_end": "2025-05-11T21:00:00",
      "test_start": "2025-05-11T22:00:00",
      "test_end": "2025-05-22T07:00:00",
      "train_samples": 1500,
      "test_samples": 250,
      "coverage": 0.72,
      "traded_samples": 180,
      "direction_accuracy": 0.524,
      "traded_direction_accuracy": 0.5222,
      "gross_return_pct": 18.7863,
      "net_return_pct": -8.2137,
      "avg_confidence": 0.3123,
      "mae": 0.007777
    },
    {
      "window_index": 113,
      "train_start": "2025-03-20T20:00:00",
      "train_end": "2025-05-22T07:00:00",
      "test_start": "2025-05-22T08:00:00",
      "test_end": "2025-06-01T17:00:00",
      "train_samples": 1500,
      "test_samples": 250,
      "coverage": 0.728,
      "traded_samples": 182,
      "direction_accuracy": 0.52,
      "traded_direction_accuracy": 0.5055,
      "gross_return_pct": -9.8889,
      "net_return_pct": -37.1889,
      "avg_confidence": 0.325,
      "mae": 0.00603
    },
    {
      "window_index": 114,
      "train_start": "2025-03-31T06:00:00",
      "train_end": "2025-06-01T17:00:00",
      "test_start": "2025-06-01T18:00:00",
      "test_end": "2025-06-12T03:00:00",
      "train_samples": 1500,
      "test_samples": 250,
      "coverage": 0.632,
      "traded_samples": 158,
      "direction_accuracy": 0.472,
      "traded_direction_accuracy": 0.4747,
      "gross_return_pct": -13.7371,
      "net_return_pct": -37.4371,
      "avg_confidence": 0.2763,
      "mae": 0.005206
    },
    {
      "window_index": 115,
      "train_start": "2025-04-10T16:00:00",
      "train_end": "2025-06-12T03:00:00",
      "test_start": "2025-06-12T04:00:00",
      "test_end": "2025-06-22T13:00:00",
      "train_samples": 1500,
      "test_samples": 250,
      "coverage": 0.736,
      "traded_samples": 184,
      "direction_accuracy": 0.496,
      "traded_direction_accuracy": 0.5,
      "gross_return_pct": -5.3913,
      "net_return_pct": -32.9913,
      "avg_confidence": 0.3035,
      "mae": 0.005707
    },
    {
      "window_index": 116,
      "train_start": "2025-04-21T02:00:00",
      "train_end": "2025-06-22T13:00:00",
      "test_start": "2025-06-22T14:00:00",
      "test_end": "2025-07-02T23:00:00",
      "train_samples": 1500,
      "test_samples": 250,
      "coverage": 0.684,
      "traded_samples": 171,
      "direction_accuracy": 0.548,
      "traded_direction_accuracy": 0.5497,
      "gross_return_pct": 7.4558,
      "net_return_pct": -18.1942,
      "avg_confidence": 0.281,
      "mae": 0.005633
    },
    {
      "window_index": 117,
      "train_start": "2025-05-01T12:00:00",
      "train_end": "2025-07-02T23:00:00",
      "test_start": "2025-07-03T00:00:00",
      "test_end": "2025-07-13T09:00:00",
      "train_samples": 1500,
      "test_samples": 250,
      "coverage": 0.708,
      "traded_samples": 177,
      "direction_accuracy": 0.576,
      "traded_direction_accuracy": 0.5706,
      "gross_return_pct": 10.7963,
      "net_return_pct": -15.7537,
      "avg_confidence": 0.3036,
      "mae": 0.006231
    },
    {
      "window_index": 118,
      "train_start": "2025-05-11T22:00:00",
      "train_end": "2025-07-13T09:00:00",
      "test_start": "2025-07-13T10:00:00",
      "test_end": "2025-07-23T19:00:00",
      "train_samples": 1500,
      "test_samples": 250,
      "coverage": 0.7,
      "traded_samples": 175,
      "direction_accuracy": 0.528,
      "traded_direction_accuracy": 0.5371,
      "gross_return_pct": 14.095,
      "net_return_pct": -12.155,
      "avg_confidence": 0.2843,
      "mae": 0.008134
    },
    {
      "window_index": 119,
      "train_start": "2025-05-22T08:00:00",
      "train_end": "2025-07-23T19:00:00",
      "test_start": "2025-07-23T20:00:00",
      "test_end": "2025-08-03T05:00:00",
      "train_samples": 1500,
      "test_samples": 250,
      "coverage": 0.668,
      "traded_samples": 167,
      "direction_accuracy": 0.536,
      "traded_direction_accuracy": 0.5389,
      "gross_return_pct": -4.0099,
      "net_return_pct": -29.0599,
      "avg_confidence": 0.2814,
      "mae": 0.006483
    },
    {
      "window_index": 120,
      "train_start": "2025-06-01T18:00:00",
      "train_end": "2025-08-03T05:00:00",
      "test_start": "2025-08-03T06:00:00",
      "test_end": "2025-08-13T15:00:00",
      "train_samples": 1500,
      "test_samples": 250,
      "coverage": 0.712,
      "traded_samples": 178,
      "direction_accuracy": 0.5,
      "traded_direction_accuracy": 0.4831,
      "gross_return_pct": -7.6894,
      "net_return_pct": -34.3894,
      "avg_confidence": 0.2883,
      "mae": 0.006152
    },
    {
      "window_index": 121,
      "train_start": "2025-06-12T04:00:00",
      "train_end": "2025-08-13T15:00:00",
      "test_start": "2025-08-13T16:00:00",
      "test_end": "2025-08-24T01:00:00",
      "train_samples": 1500,
      "test_samples": 250,
      "coverage": 0.696,
      "traded_samples": 174,
      "direction_accuracy": 0.484,
      "traded_direction_accuracy": 0.4713,
      "gross_return_pct": -33.4078,
      "net_return_pct": -59.5078,
      "avg_confidence": 0.2856,
      "mae": 0.008412
    },
    {
      "window_index": 122,
      "train_start": "2025-06-22T14:00:00",
      "train_end": "2025-08-24T01:00:00",
      "test_start": "2025-08-24T02:00:00",
      "test_end": "2025-09-03T11:00:00",
      "train_samples": 1500,
      "test_samples": 250,
      "coverage": 0.668,
      "traded_samples": 167,
      "direction_accuracy": 0.48,
      "traded_direction_accuracy": 0.491,
      "gross_return_pct": -6.9911,
      "net_return_pct": -32.0411,
      "avg_confidence": 0.2578,
      "mae": 0.006169
    },
    {
      "window_index": 123,
      "train_start": "2025-07-03T00:00:00",
      "train_end": "2025-09-03T11:00:00",
      "test_start": "2025-09-03T12:00:00",
      "test_end": "2025-09-13T21:00:00",
      "train_samples": 1500,
      "test_samples": 250,
      "coverage": 0.764,
      "traded_samples": 191,
      "direction_accuracy": 0.58,
      "traded_direction_accuracy": 0.5864,
      "gross_return_pct": 15.7306,
      "net_return_pct": -12.9194,
      "avg_confidence": 0.3197,
      "mae": 0.004066
    },
    {
      "window_index": 124,
      "train_start": "2025-07-13T10:00:00",
      "train_end": "2025-09-13T21:00:00",
      "test_start": "2025-09-13T22:00:00",
      "test_end": "2025-09-24T07:00:00",
      "train_samples": 1500,
      "test_samples": 250,
      "coverage": 0.76,
      "traded_samples": 190,
      "direction_accuracy": 0.536,
      "traded_direction_accuracy": 0.5158,
      "gross_return_pct": -1.1588,
      "net_return_pct": -29.6588,
      "avg_confidence": 0.338,
      "mae": 0.004822
    },
    {
      "window_index": 125,
      "train_start": "2025-07-23T20:00:00",
      "train_end": "2025-09-24T07:00:00",
      "test_start": "2025-09-24T08:00:00",
      "test_end": "2025-10-04T17:00:00",
      "train_samples": 1500,
      "test_samples": 250,
      "coverage": 0.684,
      "traded_samples": 171,
      "direction_accuracy": 0.508,
      "traded_direction_accuracy": 0.4912,
      "gross_return_pct": -4.0513,
      "net_return_pct": -29.7013,
      "avg_confidence": 0.2946,
      "mae": 0.004882
    },
    {
      "window_index": 126,
      "train_start": "2025-08-03T06:00:00",
      "train_end": "2025-10-04T17:00:00",
      "test_start": "2025-10-04T18:00:00",
      "test_end": "2025-10-15T03:00:00",
      "train_samples": 1500,
      "test_samples": 250,
      "coverage": 0.792,
      "traded_samples": 198,
      "direction_accuracy": 0.504,
      "traded_direction_accuracy": 0.4949,
      "gross_return_pct": -17.8395,
      "net_return_pct": -47.5395,
      "avg_confidence": 0.3621,
      "mae": 0.007814
    },
    {
      "window_index": 127,
      "train_start": "2025-08-13T16:00:00",
      "train_end": "2025-10-15T03:00:00",
      "test_start": "2025-10-15T04:00:00",
      "test_end": "2025-10-25T13:00:00",
      "train_samples": 1500,
      "test_samples": 250,
      "coverage": 0.724,
      "traded_samples": 181,
      "direction_accuracy": 0.544,
      "traded_direction_accuracy": 0.5635,
      "gross_return_pct": 6.4113,
      "net_return_pct": -20.7387,
      "avg_confidence": 0.3025,
      "mae": 0.005649
    },
    {
      "window_index": 128,
      "train_start": "2025-08-24T02:00:00",
      "train_end": "2025-10-25T13:00:00",
      "test_start": "2025-10-25T14:00:00",
      "test_end": "2025-11-04T23:00:00",
      "train_samples": 1500,
      "test_samples": 250,
      "coverage": 0.668,
      "traded_samples": 167,
      "direction_accuracy": 0.544,
      "traded_direction_accuracy": 0.5868,
      "gross_return_pct": 14.4216,
      "net_return_pct": -10.6284,
      "avg_confidence": 0.2925,
      "mae": 0.00635
    },
    {
      "window_index": 129,
      "train_start": "2025-09-03T12:00:00",
      "train_end": "2025-11-04T23:00:00",
      "test_start": "2025-11-05T00:00:00",
      "test_end": "2025-11-15T09:00:00",
      "train_samples": 1500,
      "test_samples": 250,
      "coverage": 0.728,
      "traded_samples": 182,
      "direction_accuracy": 0.536,
      "traded_direction_accuracy": 0.5165,
      "gross_return_pct": 28.5326,
      "net_return_pct": 1.2326,
      "avg_confidence": 0.2996,
      "mae": 0.007638
    },
    {
      "window_index": 130,
      "train_start": "2025-09-13T22:00:00",
      "train_end": "2025-11-15T09:00:00",
      "test_start": "2025-11-15T10:00:00",
      "test_end": "2025-11-25T19:00:00",
      "train_samples": 1500,
      "test_samples": 250,
      "coverage": 0.7,
      "traded_samples": 175,
      "direction_accuracy": 0.576,
      "traded_direction_accuracy": 0.5886,
      "gross_return_pct": 31.3006,
      "net_return_pct": 5.0506,
      "avg_confidence": 0.3083,
      "mae": 0.007673
    },
    {
      "window_index": 131,
      "train_start": "2025-09-24T08:00:00",
      "train_end": "2025-11-25T19:00:00",
      "test_start": "2025-11-25T20:00:00",
      "test_end": "2025-12-06T05:00:00",
      "train_samples": 1500,
      "test_samples": 250,
      "coverage": 0.728,
      "traded_samples": 182,
      "direction_accuracy": 0.488,
      "traded_direction_accuracy": 0.489,
      "gross_return_pct": 11.7444,
      "net_return_pct": -15.5556,
      "avg_confidence": 0.3454,
      "mae": 0.005894
    },
    {
      "window_index": 132,
      "train_start": "2025-10-04T18:00:00",
      "train_end": "2025-12-06T05:00:00",
      "test_start": "2025-12-06T06:00:00",
      "test_end": "2025-12-16T15:00:00",
      "train_samples": 1500,
      "test_samples": 250,
      "coverage": 0.692,
      "traded_samples": 173,
      "direction_accuracy": 0.556,
      "traded_direction_accuracy": 0.5491,
      "gross_return_pct": 8.7135,
      "net_return_pct": -17.2365,
      "avg_confidence": 0.2843,
      "mae": 0.005841
    },
    {
      "window_index": 133,
      "train_start": "2025-10-15T04:00:00",
      "train_end": "2025-12-16T15:00:00",
      "test_start": "2025-12-16T16:00:00",
      "test_end": "2025-12-27T01:00:00",
      "train_samples": 1500,
      "test_samples": 250,
      "coverage": 0.716,
      "traded_samples": 179,
      "direction_accuracy": 0.5,
      "traded_direction_accuracy": 0.5084,
      "gross_return_pct": -4.6999,
      "net_return_pct": -31.5499,
      "avg_confidence": 0.2832,
      "mae": 0.005701
    },
    {
      "window_index": 134,
      "train_start": "2025-10-25T14:00:00",
      "train_end": "2025-12-27T01:00:00",
      "test_start": "2025-12-27T02:00:00",
      "test_end": "2026-01-06T11:00:00",
      "train_samples": 1500,
      "test_samples": 250,
      "coverage": 0.78,
      "traded_samples": 195,
      "direction_accuracy": 0.44,
      "traded_direction_accuracy": 0.4308,
      "gross_return_pct": -28.9845,
      "net_return_pct": -58.2345,
      "avg_confidence": 0.373,
      "mae": 0.00569
    },
    {
      "window_index": 135,
      "train_start": "2025-11-05T00:00:00",
      "train_end": "2026-01-06T11:00:00",
      "test_start": "2026-01-06T12:00:00",
      "test_end": "2026-01-16T21:00:00",
      "train_samples": 1500,
      "test_samples": 250,
      "coverage": 0.748,
      "traded_samples": 187,
      "direction_accuracy": 0.5,
      "traded_direction_accuracy": 0.4973,
      "gross_return_pct": -6.4498,
      "net_return_pct": -34.4998,
      "avg_confidence": 0.3208,
      "mae": 0.005965
    },
    {
      "window_index": 136,
      "train_start": "2025-11-15T10:00:00",
      "train_end": "2026-01-16T21:00:00",
      "test_start": "2026-01-16T22:00:00",
      "test_end": "2026-01-27T07:00:00",
      "train_samples": 1500,
      "test_samples": 250,
      "coverage": 0.644,
      "traded_samples": 161,
      "direction_accuracy": 0.552,
      "traded_direction_accuracy": 0.5714,
      "gross_return_pct": 7.3502,
      "net_return_pct": -16.7998,
      "avg_confidence": 0.2601,
      "mae": 0.004923
    },
    {
      "window_index": 137,
      "train_start": "2025-11-25T20:00:00",
      "train_end": "2026-01-27T07:00:00",
      "test_start": "2026-01-27T08:00:00",
      "test_end": "2026-02-06T17:00:00",
      "train_samples": 1500,
      "test_samples": 250,
      "coverage": 0.704,
      "traded_samples": 176,
      "direction_accuracy": 0.496,
      "traded_direction_accuracy": 0.4943,
      "gross_return_pct": -1.7544,
      "net_return_pct": -28.1544,
      "avg_confidence": 0.3057,
      "mae": 0.008432
    },
    {
      "window_index": 138,
      "train_start": "2025-12-06T06:00:00",
      "train_end": "2026-02-06T17:00:00",
      "test_start": "2026-02-06T18:00:00",
      "test_end": "2026-02-17T03:00:00",
      "train_samples": 1500,
      "test_samples": 250,
      "coverage": 0.736,
      "traded_samples": 184,
      "direction_accuracy": 0.488,
      "traded_direction_accuracy": 0.4946,
      "gross_return_pct": -6.8173,
      "net_return_pct": -34.4173,
      "avg_confidence": 0.284,
      "mae": 0.006002
    },
    {
      "window_index": 139,
      "train_start": "2025-12-16T16:00:00",
      "train_end": "2026-02-17T03:00:00",
      "test_start": "2026-02-17T04:00:00",
      "test_end": "2026-02-27T13:00:00",
      "train_samples": 1500,
      "test_samples": 250,
      "coverage": 0.704,
      "traded_samples": 176,
      "direction_accuracy": 0.508,
      "traded_direction_accuracy": 0.483,
      "gross_return_pct": -13.0653,
      "net_return_pct": -39.4653,
      "avg_confidence": 0.2725,
      "mae": 0.005584
    },
    {
      "window_index": 140,
      "train_start": "2025-12-27T02:00:00",
      "train_end": "2026-02-27T13:00:00",
      "test_start": "2026-02-27T14:00:00",
      "test_end": "2026-03-09T23:00:00",
      "train_samples": 1500,
      "test_samples": 250,
      "coverage": 0.58,
      "traded_samples": 145,
      "direction_accuracy": 0.524,
      "traded_direction_accuracy": 0.6069,
      "gross_return_pct": 22.9117,
      "net_return_pct": 1.1617,
      "avg_confidence": 0.238,
      "mae": 0.005824
    },
    {
      "window_index": 141,
      "train_start": "2026-01-06T12:00:00",
      "train_end": "2026-03-09T23:00:00",
      "test_start": "2026-03-10T00:00:00",
      "test_end": "2026-03-20T09:00:00",
      "train_samples": 1500,
      "test_samples": 250,
      "coverage": 0.748,
      "traded_samples": 187,
      "direction_accuracy": 0.552,
      "traded_direction_accuracy": 0.5775,
      "gross_return_pct": 13.9364,
      "net_return_pct": -14.1136,
      "avg_confidence": 0.3343,
      "mae": 0.005355
    },
    {
      "window_index": 142,
      "train_start": "2026-01-16T22:00:00",
      "train_end": "2026-03-20T09:00:00",
      "test_start": "2026-03-20T10:00:00",
      "test_end": "2026-03-30T19:00:00",
      "train_samples": 1500,
      "test_samples": 250,
      "coverage": 0.732,
      "traded_samples": 183,
      "direction_accuracy": 0.508,
      "traded_direction_accuracy": 0.5355,
      "gross_return_pct": -1.971,
      "net_return_pct": -29.421,
      "avg_confidence": 0.3211,
      "mae": 0.004204
    }
  ]
}